MANIFEST.in
l10n_cr_base_data.xml
l10n_wizard.xml
setup.py
./__init__.py
./__openerp__.py
data/account_account_template.xml
data/account_account_type.xml
data/account_chart_template.xml
data/account_tax_code_template.xml
data/account_tax_template.xml
i18n/ar.po
i18n/ca.po
i18n/da.po
i18n/es.po
i18n/es_CR.po
i18n/es_MX.po
i18n/es_PY.po
i18n/es_VE.po
i18n/fr.po
i18n/gl.po
i18n/it.po
i18n/l10n_cr.pot
i18n/mn.po
i18n/nl.po
i18n/pt.po
i18n/pt_BR.po
i18n/sl.po
i18n/tr.po
images/config_chart_l10n_cr.jpeg
images/l10n_cr_chart.jpeg
openerp_l10n_cr.egg-info/PKG-INFO
openerp_l10n_cr.egg-info/SOURCES.txt
openerp_l10n_cr.egg-info/dependency_links.txt
openerp_l10n_cr.egg-info/requires.txt
openerp_l10n_cr.egg-info/top_level.txt
static/src/img/icon.png